opendbs/__init__.py
opendbs/client.py
opendbs-1.0.1.dist-info/METADATA
opendbs-1.0.1.dist-info/WHEEL
opendbs-1.0.1.dist-info/top_level.txt
opendbs-1.0.1.dist-info/RECORD
